extras/__init__.py
extras/divide.py
extras/multiply.py
numero_uno-0.0.1.dist-info/METADATA
numero_uno-0.0.1.dist-info/WHEEL
numero_uno-0.0.1.dist-info/top_level.txt
numero_uno-0.0.1.dist-info/RECORD
